tcrboost/__init__.py
tcrboost-0.1.0.dist-info/LICENSE
tcrboost-0.1.0.dist-info/METADATA
tcrboost-0.1.0.dist-info/WHEEL
tcrboost-0.1.0.dist-info/top_level.txt
tcrboost-0.1.0.dist-info/RECORD
